alert.py
alert-0.0.1.dist-info/LICENSE.txt
alert-0.0.1.dist-info/METADATA
alert-0.0.1.dist-info/WHEEL
alert-0.0.1.dist-info/top_level.txt
alert-0.0.1.dist-info/RECORD
